csvresumable/__init__.py
csvresumable/capture.py
csvresumable/consts.py
csvresumable/langhelpers.py
csvresumable/loader.py
csvresumable/name.py
csvresumable/recorder.py
csvresumable-0.0.3.post2.dist-info/METADATA
csvresumable-0.0.3.post2.dist-info/RECORD
csvresumable-0.0.3.post2.dist-info/WHEEL
csvresumable-0.0.3.post2.dist-info/entry_points.txt
csvresumable-0.0.3.post2.dist-info/top_level.txt
