Metadata-Version: 2.1
Name: csvresumable
Version: 0.0.3.post2
Summary: adding tiny resume function, for csv reading iterator
Home-page: https://github.com/podhmo/csvresumable
Author: podhmo
Author-email: ababjam61+pypi@gmail.com
License: UNKNOWN
Keywords: csv,resume
Platform: UNKNOWN
Classifier: Programming Language :: Python
Classifier: Programming Language :: Python :: Implementation :: CPython
Provides-Extra: testing
Provides-Extra: docs
Provides-Extra: docs
Requires-Dist: kamidana; extra == 'docs'
Provides-Extra: testing
